structure2symmetry/symmetry.py
structure2symmetry/utils.py
structure2symmetry-0.0.1.dist-info/entry_points.txt
structure2symmetry-0.0.1.dist-info/LICENSE
structure2symmetry-0.0.1.dist-info/METADATA
structure2symmetry-0.0.1.dist-info/WHEEL
structure2symmetry-0.0.1.dist-info/RECORD
