Metadata-Version: 2.1
Name: structure2symmetry
Version: 0.0.1
Summary: A python package to extract symmetry information from structure files, including POSCAR, CIF, and other format supported by ase.io.read.
License: MIT
Author: Shibu Meher
Author-email: shibumeher@iisc.ac.in
Requires-Python: >=3.8,<4.0
Classifier: License :: OSI Approved :: MIT License
Classifier: Programming Language :: Python :: 3
Classifier: Programming Language :: Python :: 3.8
Classifier: Programming Language :: Python :: 3.9
Classifier: Programming Language :: Python :: 3.10
Classifier: Programming Language :: Python :: 3.11
Requires-Dist: ase (>=3.22.1,<4.0.0)
Requires-Dist: click (>=8.1.7,<9.0.0)
Requires-Dist: numpy (>=1.26.4,<2.0.0)
Requires-Dist: spglib (>=2.3.1,<3.0.0)
